setup.py
tweetbot/__init__.py
tweetbot/bot.py
tweetbot.egg-info/PKG-INFO
tweetbot.egg-info/SOURCES.txt
tweetbot.egg-info/dependency_links.txt
tweetbot.egg-info/requires.txt
tweetbot.egg-info/top_level.txt