Metadata-Version: 1.0
Name: tweetbot
Version: 0.1
Summary: A python powered twitter library.
Home-page: UNKNOWN
Author: Zach Seifts
Author-email: zach.seifts+tweetbot@gmail.com
License: BSD
Keywords: twitter bots
Platform: UNKNOWN
Classifier: Development Status :: 3 - Alpha
Classifier: Environment :: Web Environment
Classifier: Intended Audience :: Developers
Classifier: Natural Language :: English
Classifier: Operating System :: OS Independent
Classifier: License :: OSI Approved :: BSD License
Classifier: Topic :: Software Development :: Libraries :: Python Modules
Classifier: Topic :: Communications :: Chat
Classifier: Topic :: Internet
